[
  {
  "tag_id": "TagName",
  "tag_name": 79,
  "Unit": "UNIT MTS",
  "time": "just now"
  },
  {
  "tag_id": "TagName1",
  "tag_name": 29,
  "Unit": "UNIT MTS",
  "time": "just now"
  },
  {
  "tag_id": "TagName2",
  "tag_name": 102,
  "Unit": "UNIT MTS",
  "time": "just now",
  "class": "red"
  },
  {
  "tag_id": "TagName3",
  "tag_name": 79,
  "Unit": "UNIT MTS",
  "time": "just now",
  "class": "green"
  },
  {
  "tag_id": "TagName3",
  "tag_name": 79,
  "Unit": "UNIT MTS",
  "time": "just now",
  "class": "green"
  },
  {
  "tag_id": "TagName3",
  "tag_name": 79,
  "Unit": "UNIT MTS",
  "time": "just now"
  },
  {
  "tag_id": "TagName3",
  "tag_name": 79,
  "Unit": "UNIT MTS",
  "time": "just now"
  }
]
